projects/AES/simulation/trj/transmit/design.sv
module transmit (
    input [255:0] key_cpy,
    input clk,     // 50MHz clock
    input reset,   // reset signal
    output reg Ant1    // antenna output
);

reg [255:0] SHIFTReg = 0;
reg [255:0] BaudGen = 0;

// Duration calculation
parameter BEEP_DURATION = 16;
parameter PAUSE_DURATION = 16;
parameter SHORT_PAUSE_DURATION = 8;
parameter TOTAL_DURATION = 32;

reg [6:0] count = 0;
reg [4:0] bit_phase = 0;

always @(posedge clk or posedge reset) begin
    if (reset) begin
        BaudGen <= 0;
        SHIFTReg <= key_cpy;
        Ant1 <= 0;
        count <= 0;
        bit_phase <= 0;
    end else begin
        BaudGen <= BaudGen + 1;
        
        if (count == TOTAL_DURATION - 1) begin
            count <= 0;
            if (BaudGen < 255) begin
                BaudGen <= BaudGen + 1;
            end else begin
                BaudGen <= 0;
            end
            SHIFTReg <= {SHIFTReg[254:0], 0};
        end else begin
            count <= count + 1;
        end

        // Modulation logic
        if (SHIFTReg[255] == 0) begin
            // Logic for '0'
            if (bit_phase < BEEP_DURATION) begin
                Ant1 <= 1; // Beep
            end else begin
                Ant1 <= 0; // Pause
            end
        end else begin
            // Logic for '1'
            if (bit_phase < BEEP_DURATION || (bit_phase >= BEEP_DURATION + SHORT_PAUSE_DURATION && bit_phase < 2 * BEEP_DURATION + SHORT_PAUSE_DURATION)) begin
                Ant1 <= 1; // Beep
            end else begin
                Ant1 <= 0; // Pause
            end
        end
        
        if (bit_phase == TOTAL_DURATION - 1) begin
            bit_phase <= 0;
        end else begin
            bit_phase <= bit_phase + 1;
        end
    end
end

endmodule

projects/AES/simulation/trj/transmit/testbench.sv
module transmit_tb;

    reg clk;
    reg reset;
    reg [255:0] key_cpy_tb;
    wire Ant1;

    // Instantiate the module
    transmit uut (
        .clk(clk),
        .reset(reset),
        .key_cpy(key_cpy_tb),
        .Ant1(Ant1)
    );

    // Clock generation
    always begin
        #10 clk = ~clk;
    end

    // Test procedure
    initial begin
        // Initialize
        clk = 0;
        reset = 1;
        key_cpy_tb = 256'b0;
        #20 reset = 0;

        // Test case 1: Send some random data
        key_cpy_tb = 256'hABCDEF0123456789ABCDEF0123456789ABCDEF0123456789ABCDEF0123456789;
        #10000;

        // Test case 2: Send all zeros
        key_cpy_tb = 256'b0;
        #10000;

        // Test case 3: Send all ones
        key_cpy_tb = 256'b1;
        #10000;

        $stop; // Stop the simulation
    end

    // Monitor the results
    initial begin
      $dumpfile("dump.vcd"); 
      $dumpvars;
        $monitor($time, " Ant1=%b", Ant1);
    end

endmodule

projects/AES/simulation/trj/transmit.v/dump.vcd
$date
	Mon Oct 30 12:04:37 2023
$end
$version
	QuestaSim Version 2021.3
$end
$timescale
	1ns
$end

$scope module transmit_tb $end
$var reg 1 ! clk $end
$var reg 1 " reset $end
$var reg 256 # key_cpy_tb [255:0] $end
$var wire 1 $ Ant1 $end

$scope module uut $end
$var parameter 32 % BEEP_DURATION $end
$var parameter 32 & PAUSE_DURATION $end
$var parameter 32 ' SHORT_PAUSE_DURATION $end
$var parameter 32 ( TOTAL_DURATION $end
$var wire 1 ) key_cpy [255] $end
$var wire 1 * key_cpy [254] $end
$var wire 1 + key_cpy [253] $end
$var wire 1 , key_cpy [252] $end
$var wire 1 - key_cpy [251] $end
$var wire 1 . key_cpy [250] $end
$var wire 1 / key_cpy [249] $end
$var wire 1 0 key_cpy [248] $end
$var wire 1 1 key_cpy [247] $end
$var wire 1 2 key_cpy [246] $end
$var wire 1 3 key_cpy [245] $end
$var wire 1 4 key_cpy [244] $end
$var wire 1 5 key_cpy [243] $end
$var wire 1 6 key_cpy [242] $end
$var wire 1 7 key_cpy [241] $end
$var wire 1 8 key_cpy [240] $end
$var wire 1 9 key_cpy [239] $end
$var wire 1 : key_cpy [238] $end
$var wire 1 ; key_cpy [237] $end
$var wire 1 < key_cpy [236] $end
$var wire 1 = key_cpy [235] $end
$var wire 1 > key_cpy [234] $end
$var wire 1 ? key_cpy [233] $end
$var wire 1 @ key_cpy [232] $end
$var wire 1 A key_cpy [231] $end
$var wire 1 B key_cpy [230] $end
$var wire 1 C key_cpy [229] $end
$var wire 1 D key_cpy [228] $end
$var wire 1 E key_cpy [227] $end
$var wire 1 F key_cpy [226] $end
$var wire 1 G key_cpy [225] $end
$var wire 1 H key_cpy [224] $end
$var wire 1 I key_cpy [223] $end
$var wire 1 J key_cpy [222] $end
$var wire 1 K key_cpy [221] $end
$var wire 1 L key_cpy [220] $end
$var wire 1 M key_cpy [219] $end
$var wire 1 N key_cpy [218] $end
$var wire 1 O key_cpy [217] $end
$var wire 1 P key_cpy [216] $end
$var wire 1 Q key_cpy [215] $end
$var wire 1 R key_cpy [214] $end
$var wire 1 S key_cpy [213] $end
$var wire 1 T key_cpy [212] $end
$var wire 1 U key_cpy [211] $end
$var wire 1 V key_cpy [210] $end
$var wire 1 W key_cpy [209] $end
$var wire 1 X key_cpy [208] $end
$var wire 1 Y key_cpy [207] $end
$var wire 1 Z key_cpy [206] $end
$var wire 1 [ key_cpy [205] $end
$var wire 1 \ key_cpy [204] $end
$var wire 1 ] key_cpy [203] $end
$var wire 1 ^ key_cpy [202] $end
$var wire 1 _ key_cpy [201] $end
$var wire 1 ` key_cpy [200] $end
$var wire 1 a key_cpy [199] $end
$var wire 1 b key_cpy [198] $end
$var wire 1 c key_cpy [197] $end
$var wire 1 d key_cpy [196] $end
$var wire 1 e key_cpy [195] $end
$var wire 1 f key_cpy [194] $end
$var wire 1 g key_cpy [193] $end
$var wire 1 h key_cpy [192] $end
$var wire 1 i key_cpy [191] $end
$var wire 1 j key_cpy [190] $end
$var wire 1 k key_cpy [189] $end
$var wire 1 l key_cpy [188] $end
$var wire 1 m key_cpy [187] $end
$var wire 1 n key_cpy [186] $end
$var wire 1 o key_cpy [185] $end
$var wire 1 p key_cpy [184] $end
$var wire 1 q key_cpy [183] $end
$var wire 1 r key_cpy [182] $end
$var wire 1 s key_cpy [181] $end
$var wire 1 t key_cpy [180] $end
$var wire 1 u key_cpy [179] $end
$var wire 1 v key_cpy [178] $end
$var wire 1 w key_cpy [177] $end
$var wire 1 x key_cpy [176] $end
$var wire 1 y key_cpy [175] $end
$var wire 1 z key_cpy [174] $end
$var wire 1 { key_cpy [173] $end
$var wire 1 | key_cpy [172] $end
$var wire 1 } key_cpy [171] $end
$var wire 1 ~ key_cpy [170] $end
$var wire 1 !! key_cpy [169] $end
$var wire 1 "! key_cpy [168] $end
$var wire 1 #! key_cpy [167] $end
$var wire 1 $! key_cpy [166] $end
$var wire 1 %! key_cpy [165] $end
$var wire 1 &! key_cpy [164] $end
$var wire 1 '! key_cpy [163] $end
$var wire 1 (! key_cpy [162] $end
$var wire 1 )! key_cpy [161] $end
$var wire 1 *! key_cpy [160] $end
$var wire 1 +! key_cpy [159] $end
$var wire 1 ,! key_cpy [158] $end
$var wire 1 -! key_cpy [157] $end
$var wire 1 .! key_cpy [156] $end
$var wire 1 /! key_cpy [155] $end
$var wire 1 0! key_cpy [154] $end
$var wire 1 1! key_cpy [153] $end
$var wire 1 2! key_cpy [152] $end
$var wire 1 3! key_cpy [151] $end
$var wire 1 4! key_cpy [150] $end
$var wire 1 5! key_cpy [149] $end
$var wire 1 6! key_cpy [148] $end
$var wire 1 7! key_cpy [147] $end
$var wire 1 8! key_cpy [146] $end
$var wire 1 9! key_cpy [145] $end
$var wire 1 :! key_cpy [144] $end
$var wire 1 ;! key_cpy [143] $end
$var wire 1 <! key_cpy [142] $end
$var wire 1 =! key_cpy [141] $end
$var wire 1 >! key_cpy [140] $end
$var wire 1 ?! key_cpy [139] $end
$var wire 1 @! key_cpy [138] $end
$var wire 1 A! key_cpy [137] $end
$var wire 1 B! key_cpy [136] $end
$var wire 1 C! key_cpy [135] $end
$var wire 1 D! key_cpy [134] $end
$var wire 1 E! key_cpy [133] $end
$var wire 1 F! key_cpy [132] $end
$var wire 1 G! key_cpy [131] $end
$var wire 1 H! key_cpy [130] $end
$var wire 1 I! key_cpy [129] $end
$var wire 1 J! key_cpy [128] $end
$var wire 1 K! key_cpy [127] $end
$var wire 1 L! key_cpy [126] $end
$var wire 1 M! key_cpy [125] $end
$var wire 1 N! key_cpy [124] $end
$var wire 1 O! key_cpy [123] $end
$var wire 1 P! key_cpy [122] $end
$var wire 1 Q! key_cpy [121] $end
$var wire 1 R! key_cpy [120] $end
$var wire 1 S! key_cpy [119] $end
$var wire 1 T! key_cpy [118] $end
$var wire 1 U! key_cpy [117] $end
$var wire 1 V! key_cpy [116] $end
$var wire 1 W! key_cpy [115] $end
$var wire 1 X! key_cpy [114] $end
$var wire 1 Y! key_cpy [113] $end
$var wire 1 Z! key_cpy [112] $end
$var wire 1 [! key_cpy [111] $end
$var wire 1 \! key_cpy [110] $end
$var wire 1 ]! key_cpy [109] $end
$var wire 1 ^! key_cpy [108] $end
$var wire 1 _! key_cpy [107] $end
$var wire 1 `! key_cpy [106] $end
$var wire 1 a! key_cpy [105] $end
$var wire 1 b! key_cpy [104] $end
$var wire 1 c! key_cpy [103] $end
$var wire 1 d! key_cpy [102] $end
$var wire 1 e! key_cpy [101] $end
$var wire 1 f! key_cpy [100] $end
$var wire 1 g! key_cpy [99] $end
$var wire 1 h! key_cpy [98] $end
$var wire 1 i! key_cpy [97] $end
$var wire 1 j! key_cpy [96] $end
$var wire 1 k! key_cpy [95] $end
$var wire 1 l! key_cpy [94] $end
$var wire 1 m! key_cpy [93] $end
$var wire 1 n! key_cpy [92] $end
$var wire 1 o! key_cpy [91] $end
$var wire 1 p! key_cpy [90] $end
$var wire 1 q! key_cpy [89] $end
$var wire 1 r! key_cpy [88] $end
$var wire 1 s! key_cpy [87] $end
$var wire 1 t! key_cpy [86] $end
$var wire 1 u! key_cpy [85] $end
$var wire 1 v! key_cpy [84] $end
$var wire 1 w! key_cpy [83] $end
$var wire 1 x! key_cpy [82] $end
$var wire 1 y! key_cpy [81] $end
$var wire 1 z! key_cpy [80] $end
$var wire 1 {! key_cpy [79] $end
$var wire 1 |! key_cpy [78] $end
$var wire 1 }! key_cpy [77] $end
$var wire 1 ~! key_cpy [76] $end
$var wire 1 !" key_cpy [75] $end
$var wire 1 "" key_cpy [74] $end
$var wire 1 #" key_cpy [73] $end
$var wire 1 $" key_cpy [72] $end
$var wire 1 %" key_cpy [71] $end
$var wire 1 &" key_cpy [70] $end
$var wire 1 '" key_cpy [69] $end
$var wire 1 (" key_cpy [68] $end
$var wire 1 )" key_cpy [67] $end
$var wire 1 *" key_cpy [66] $end
$var wire 1 +" key_cpy [65] $end
$var wire 1 ," key_cpy [64] $end
$var wire 1 -" key_cpy [63] $end
$var wire 1 ." key_cpy [62] $end
$var wire 1 /" key_cpy [61] $end
$var wire 1 0" key_cpy [60] $end
$var wire 1 1" key_cpy [59] $end
$var wire 1 2" key_cpy [58] $end
$var wire 1 3" key_cpy [57] $end
$var wire 1 4" key_cpy [56] $end
$var wire 1 5" key_cpy [55] $end
$var wire 1 6" key_cpy [54] $end
$var wire 1 7" key_cpy [53] $end
$var wire 1 8" key_cpy [52] $end
$var wire 1 9" key_cpy [51] $end
$var wire 1 :" key_cpy [50] $end
$var wire 1 ;" key_cpy [49] $end
$var wire 1 <" key_cpy [48] $end
$var wire 1 =" key_cpy [47] $end
$var wire 1 >" key_cpy [46] $end
$var wire 1 ?" key_cpy [45] $end
$var wire 1 @" key_cpy [44] $end
$var wire 1 A" key_cpy [43] $end
$var wire 1 B" key_cpy [42] $end
$var wire 1 C" key_cpy [41] $end
$var wire 1 D" key_cpy [40] $end
$var wire 1 E" key_cpy [39] $end
$var wire 1 F" key_cpy [38] $end
$var wire 1 G" key_cpy [37] $end
$var wire 1 H" key_cpy [36] $end
$var wire 1 I" key_cpy [35] $end
$var wire 1 J" key_cpy [34] $end
$var wire 1 K" key_cpy [33] $end
$var wire 1 L" key_cpy [32] $end
$var wire 1 M" key_cpy [31] $end
$var wire 1 N" key_cpy [30] $end
$var wire 1 O" key_cpy [29] $end
$var wire 1 P" key_cpy [28] $end
$var wire 1 Q" key_cpy [27] $end
$var wire 1 R" key_cpy [26] $end
$var wire 1 S" key_cpy [25] $end
$var wire 1 T" key_cpy [24] $end
$var wire 1 U" key_cpy [23] $end
$var wire 1 V" key_cpy [22] $end
$var wire 1 W" key_cpy [21] $end
$var wire 1 X" key_cpy [20] $end
$var wire 1 Y" key_cpy [19] $end
$var wire 1 Z" key_cpy [18] $end
$var wire 1 [" key_cpy [17] $end
$var wire 1 \" key_cpy [16] $end
$var wire 1 ]" key_cpy [15] $end
$var wire 1 ^" key_cpy [14] $end
$var wire 1 _" key_cpy [13] $end
$var wire 1 `" key_cpy [12] $end
$var wire 1 a" key_cpy [11] $end
$var wire 1 b" key_cpy [10] $end
$var wire 1 c" key_cpy [9] $end
$var wire 1 d" key_cpy [8] $end
$var wire 1 e" key_cpy [7] $end
$var wire 1 f" key_cpy [6] $end
$var wire 1 g" key_cpy [5] $end
$var wire 1 h" key_cpy [4] $end
$var wire 1 i" key_cpy [3] $end
$var wire 1 j" key_cpy [2] $end
$var wire 1 k" key_cpy [1] $end
$var wire 1 l" key_cpy [0] $end
$var wire 1 m" clk $end
$var wire 1 n" reset $end
$var reg 1 o" Ant1 $end
$var reg 256 p" SHIFTReg [255:0] $end
$var reg 256 q" BaudGen [255:0] $end
$var reg 7 r" count [6:0] $end
$var reg 5 s" bit_phase [4:0] $end
$upscope $end
$upscope $end

$scope begin std $end
$upscope $end
$enddefinitions $end
#0
$dumpvars
0!
1"
b0 #
0o"
b0 p"
b0 q"
b0 r"
b0 s"
b10000 %
b10000 &
b1000 '
b100000 (
0$
1n"
0m"
0l"
0k"
0j"
0i"
0h"
0g"
0f"
0e"
0d"
0c"
0b"
0a"
0`"
0_"
0^"
0]"
0\"
0["
0Z"
0Y"
0X"
0W"
0V"
0U"
0T"
0S"
0R"
0Q"
0P"
0O"
0N"
0M"
0L"
0K"
0J"
0I"
0H"
0G"
0F"
0E"
0D"
0C"
0B"
0A"
0@"
0?"
0>"
0="
0<"
0;"
0:"
09"
08"
07"
06"
05"
04"
03"
02"
01"
00"
0/"
0."
0-"
0,"
0+"
0*"
0)"
0("
0'"
0&"
0%"
0$"
0#"
0""
0!"
0~!
0}!
0|!
0{!
0z!
0y!
0x!
0w!
0v!
0u!
0t!
0s!
0r!
0q!
0p!
0o!
0n!
0m!
0l!
0k!
0j!
0i!
0h!
0g!
0f!
0e!
0d!
0c!
0b!
0a!
0`!
0_!
0^!
0]!
0\!
0[!
0Z!
0Y!
0X!
0W!
0V!
0U!
0T!
0S!
0R!
0Q!
0P!
0O!
0N!
0M!
0L!
0K!
0J!
0I!
0H!
0G!
0F!
0E!
0D!
0C!
0B!
0A!
0@!
0?!
0>!
0=!
0<!
0;!
0:!
09!
08!
07!
06!
05!
04!
03!
02!
01!
00!
0/!
0.!
0-!
0,!
0+!
0*!
0)!
0(!
0'!
0&!
0%!
0$!
0#!
0"!
0!!
0~
0}
0|
0{
0z
0y
0x
0w
0v
0u
0t
0s
0r
0q
0p
0o
0n
0m
0l
0k
0j
0i
0h
0g
0f
0e
0d
0c
0b
0a
0`
0_
0^
0]
0\
0[
0Z
0Y
0X
0W
0V
0U
0T
0S
0R
0Q
0P
0O
0N
0M
0L
0K
0J
0I
0H
0G
0F
0E
0D
0C
0B
0A
0@
0?
0>
0=
0<
0;
0:
09
08
07
06
05
04
03
02
01
00
0/
0.
0-
0,
0+
0*
0)
$end
#10
1!
1m"
#20
0"
b1010101111001101111011110000000100100011010001010110011110001001101010111100110111101111000000010010001101000101011001111000100110101011110011011110111100000001001000110100010101100111100010011010101111001101111011110000000100100011010001010110011110001001 #
0!
1l"
1i"
1e"
1d"
1c"
1b"
1_"
1^"
1\"
1Z"
1V"
1T"
1S"
1O"
1L"
1D"
1C"
1B"
1A"
1?"
1>"
1="
1<"
1:"
19"
16"
15"
14"
13"
11"
1/"
1-"
1,"
1)"
1%"
1$"
1#"
1""
1}!
1|!
1z!
1x!
1t!
1r!
1q!
1m!
1j!
1b!
1a!
1`!
1_!
1]!
1\!
1[!
1Z!
1X!
1W!
1T!
1S!
1R!
1Q!
1O!
1M!
1K!
1J!
1G!
1C!
1B!
1A!
1@!
1=!
1<!
1:!
18!
14!
12!
11!
1-!
1*!
1"!
1!!
1~
1}
1{
1z
1y
1x
1v
1u
1r
1q
1p
1o
1m
1k
1i
1h
1e
1a
1`
1_
1^
1[
1Z
1X
1V
1R
1P
1O
1K
1H
1@
1?
1>
1=
1;
1:
19
18
16
15
12
11
10
1/
1-
1+
1)
0n"
0m"
#30
1!
1m"
b1 q"
b1 r"
1o"
b1 s"
1$
#40
0!
0m"
#50
1!
1m"
b10 q"
b10 r"
b10 s"
#60
0!
0m"
#70
1!
1m"
b11 q"
b11 r"
b11 s"
#80
0!
0m"
#90
1!
1m"
b100 q"
b100 r"
b100 s"
#100
0!
0m"
#110
1!
1m"
b101 q"
b101 r"
b101 s"
#120
0!
0m"
#130
1!
1m"
b110 q"
b110 r"
b110 s"
#140
0!
0m"
#150
1!
1m"
b111 q"
b111 r"
b111 s"
#160
0!
0m"
#170
1!
1m"
b1000 q"
b1000 r"
b1000 s"
#180
0!
0m"
#190
1!
1m"
b1001 q"
b1001 r"
b1001 s"
#200
0!
0m"
#210
1!
1m"
b1010 q"
b1010 r"
b1010 s"
#220
0!
0m"
#230
1!
1m"
b1011 q"
b1011 r"
b1011 s"
#240
0!
0m"
#250
1!
1m"
b1100 q"
b1100 r"
b1100 s"
#260
0!
0m"
#270
1!
1m"
b1101 q"
b1101 r"
b1101 s"
#280
0!
0m"
#290
1!
1m"
b1110 q"
b1110 r"
b1110 s"
#300
0!
0m"
#310
1!
1m"
b1111 q"
b1111 r"
b1111 s"
#320
0!
0m"
#330
1!
1m"
b10000 q"
b10000 r"
b10000 s"
#340
0!
0m"
#350
1!
1m"
b10001 q"
b10001 r"
0o"
b10001 s"
0$
#360
0!
0m"
#370
1!
1m"
b10010 q"
b10010 r"
b10010 s"
#380
0!
0m"
#390
1!
1m"
b10011 q"
b10011 r"
b10011 s"
#400
0!
0m"
#410
1!
1m"
b10100 q"
b10100 r"
b10100 s"
#420
0!
0m"
#430
1!
1m"
b10101 q"
b10101 r"
b10101 s"
#440
0!
0m"
#450
1!
1m"
b10110 q"
b10110 r"
b10110 s"
#460
0!
0m"
#470
1!
1m"
b10111 q"
b10111 r"
b10111 s"
#480
0!
0m"
#490
1!
1m"
b11000 q"
b11000 r"
b11000 s"
#500
0!
0m"
#510
1!
1m"
b11001 q"
b11001 r"
b11001 s"
#520
0!
0m"
#530
1!
1m"
b11010 q"
b11010 r"
b11010 s"
#540
0!
0m"
#550
1!
1m"
b11011 q"
b11011 r"
b11011 s"
#560
0!
0m"
#570
1!
1m"
b11100 q"
b11100 r"
b11100 s"
#580
0!
0m"
#590
1!
1m"
b11101 q"
b11101 r"
b11101 s"
#600
0!
0m"
#610
1!
1m"
b11110 q"
b11110 r"
b11110 s"
#620
0!
0m"
#630
1!
1m"
b11111 q"
b11111 r"
b11111 s"
#640
0!
0m"
#650
1!
1m"
b100000 q"
b0 r"
b0 s"
#660
0!
0m"
#670
1!
1m"
b100001 q"
b1 r"
1o"
b1 s"
1$
#680
0!
0m"
#690
1!
1m"
b100010 q"
b10 r"
b10 s"
#700
0!
0m"
#710
1!
1m"
b100011 q"
b11 r"
b11 s"
#720
0!
0m"
#730
1!
1m"
b100100 q"
b100 r"
b100 s"
#740
0!
0m"
#750
1!
1m"
b100101 q"
b101 r"
b101 s"
#760
0!
0m"
#770
1!
1m"
b100110 q"
b110 r"
b110 s"
#780
0!
0m"
#790
1!
1m"
b100111 q"
b111 r"
b111 s"
#800
0!
0m"
#810
1!
1m"
b101000 q"
b1000 r"
b1000 s"
#820
0!
0m"
#830
1!
1m"
b101001 q"
b1001 r"
b1001 s"
#840
0!
0m"
#850
1!
1m"
b101010 q"
b1010 r"
b1010 s"
#860
0!
0m"
#870
1!
1m"
b101011 q"
b1011 r"
b1011 s"
#880
0!
0m"
#890
1!
1m"
b101100 q"
b1100 r"
b1100 s"
#900
0!
0m"
#910
1!
1m"
b101101 q"
b1101 r"
b1101 s"
#920
0!
0m"
#930
1!
1m"
b101110 q"
b1110 r"
b1110 s"
#940
0!
0m"
#950
1!
1m"
b101111 q"
b1111 r"
b1111 s"
#960
0!
0m"
#970
1!
1m"
b110000 q"
b10000 r"
b10000 s"
#980
0!
0m"
#990
1!
1m"
b110001 q"
b10001 r"
0o"
b10001 s"
0$
#1000
0!
0m"
#1010
1!
1m"
b110010 q"
b10010 r"
b10010 s"
#1020
0!
0m"
#1030
1!
1m"
b110011 q"
b10011 r"
b10011 s"
#1040
0!
0m"
#1050
1!
1m"
b110100 q"
b10100 r"
b10100 s"
#1060
0!
0m"
#1070
1!
1m"
b110101 q"
b10101 r"
b10101 s"
#1080
0!
0m"
#1090
1!
1m"
b110110 q"
b10110 r"
b10110 s"
#1100
0!
0m"
#1110
1!
1m"
b110111 q"
b10111 r"
b10111 s"
#1120
0!
0m"
#1130
1!
1m"
b111000 q"
b11000 r"
b11000 s"
#1140
0!
0m"
#1150
1!
1m"
b111001 q"
b11001 r"
b11001 s"
#1160
0!
0m"
#1170
1!
1m"
b111010 q"
b11010 r"
b11010 s"
#1180
0!
0m"
#1190
1!
1m"
b111011 q"
b11011 r"
b11011 s"
#1200
0!
0m"
#1210
1!
1m"
b111100 q"
b11100 r"
b11100 s"
#1220
0!
0m"
#1230
1!
1m"
b111101 q"
b11101 r"
b11101 s"
#1240
0!
0m"
#1250
1!
1m"
b111110 q"
b11110 r"
b11110 s"
#1260
0!
0m"
#1270
1!
1m"
b111111 q"
b11111 r"
b11111 s"
#1280
0!
0m"
#1290
1!
1m"
b1000000 q"
b0 r"
b0 s"
#1300
0!
0m"
#1310
1!
1m"
b1000001 q"
b1 r"
1o"
b1 s"
1$
#1320
0!
0m"
#1330
1!
1m"
b1000010 q"
b10 r"
b10 s"
#1340
0!
0m"
#1350
1!
1m"
b1000011 q"
b11 r"
b11 s"
#1360
0!
0m"
#1370
1!
1m"
b1000100 q"
b100 r"
b100 s"
#1380
0!
0m"
#1390
1!
1m"
b1000101 q"
b101 r"
b101 s"
#1400
0!
0m"
#1410
1!
1m"
b1000110 q"
b110 r"
b110 s"
#1420
0!
0m"
#1430
1!
1m"
b1000111 q"
b111 r"
b111 s"
#1440
0!
0m"
#1450
1!
1m"
b1001000 q"
b1000 r"
b1000 s"
#1460
0!
0m"
#1470
1!
1m"
b1001001 q"
b1001 r"
b1001 s"
#1480
0!
0m"
#1490
1!
1m"
b1001010 q"
b1010 r"
b1010 s"
#1500
0!
0m"
#1510
1!
1m"
b1001011 q"
b1011 r"
b1011 s"
#1520
0!
0m"
#1530
1!
1m"
b1001100 q"
b1100 r"
b1100 s"
#1540
0!
0m"
#1550
1!
1m"
b1001101 q"
b1101 r"
b1101 s"
#1560
0!
0m"
#1570
1!
1m"
b1001110 q"
b1110 r"
b1110 s"
#1580
0!
0m"
#1590
1!
1m"
b1001111 q"
b1111 r"
b1111 s"
#1600
0!
0m"
#1610
1!
1m"
b1010000 q"
b10000 r"
b10000 s"
#1620
0!
0m"
#1630
1!
1m"
b1010001 q"
b10001 r"
0o"
b10001 s"
0$
#1640
0!
0m"
#1650
1!
1m"
b1010010 q"
b10010 r"
b10010 s"
#1660
0!
0m"
#1670
1!
1m"
b1010011 q"
b10011 r"
b10011 s"
#1680
0!
0m"
#1690
1!
1m"
b1010100 q"
b10100 r"
b10100 s"
#1700
0!
0m"
#1710
1!
1m"
b1010101 q"
b10101 r"
b10101 s"
#1720
0!
0m"
#1730
1!
1m"
b1010110 q"
b10110 r"
b10110 s"
#1740
0!
0m"
#1750
1!
1m"
b1010111 q"
b10111 r"
b10111 s"
#1760
0!
0m"
#1770
1!
1m"
b1011000 q"
b11000 r"
b11000 s"
#1780
0!
0m"
#1790
1!
1m"
b1011001 q"
b11001 r"
b11001 s"
#1800
0!
0m"
#1810
1!
1m"
b1011010 q"
b11010 r"
b11010 s"
#1820
0!
0m"
#1830
1!
1m"
b1011011 q"
b11011 r"
b11011 s"
#1840
0!
0m"
#1850
1!
1m"
b1011100 q"
b11100 r"
b11100 s"
#1860
0!
0m"
#1870
1!
1m"
b1011101 q"
b11101 r"
b11101 s"
#1880
0!
0m"
#1890
1!
1m"
b1011110 q"
b11110 r"
b11110 s"
#1900
0!
0m"
#1910
1!
1m"
b1011111 q"
b11111 r"
b11111 s"
#1920
0!
0m"
#1930
1!
1m"
b1100000 q"
b0 r"
b0 s"
#1940
0!
0m"
#1950
1!
1m"
b1100001 q"
b1 r"
1o"
b1 s"
1$
#1960
0!
0m"
#1970
1!
1m"
b1100010 q"
b10 r"
b10 s"
#1980
0!
0m"
#1990
1!
1m"
b1100011 q"
b11 r"
b11 s"
#2000
0!
0m"
#2010
1!
1m"
b1100100 q"
b100 r"
b100 s"
#2020
0!
0m"
#2030
1!
1m"
b1100101 q"
b101 r"
b101 s"
#2040
0!
0m"
#2050
1!
1m"
b1100110 q"
b110 r"
b110 s"
#2060
0!
0m"
#2070
1!
1m"
b1100111 q"
b111 r"
b111 s"
#2080
0!
0m"
#2090
1!
1m"
b1101000 q"
b1000 r"
b1000 s"
#2100
0!
0m"
#2110
1!
1m"
b1101001 q"
b1001 r"
b1001 s"
#2120
0!
0m"
#2130
1!
1m"
b1101010 q"
b1010 r"
b1010 s"
#2140
0!
0m"
#2150
1!
1m"
b1101011 q"
b1011 r"
b1011 s"
#2160
0!
0m"
#2170
1!
1m"
b1101100 q"
b1100 r"
b1100 s"
#2180
0!
0m"
#2190
1!
1m"
b1101101 q"
b1101 r"
b1101 s"
#2200
0!
0m"
#2210
1!
1m"
b1101110 q"
b1110 r"
b1110 s"
#2220
0!
0m"
#2230
1!
1m"
b1101111 q"
b1111 r"
b1111 s"
#2240
0!
0m"
#2250
1!
1m"
b1110000 q"
b10000 r"
b10000 s"
#2260
0!
0m"
#2270
1!
1m"
b1110001 q"
b10001 r"
0o"
b10001 s"
0$
#2280
0!
0m"
#2290
1!
1m"
b1110010 q"
b10010 r"
b10010 s"
#2300
0!
0m"
#2310
1!
1m"
b1110011 q"
b10011 r"
b10011 s"
#2320
0!
0m"
#2330
1!
1m"
b1110100 q"
b10100 r"
b10100 s"
#2340
0!
0m"
#2350
1!
1m"
b1110101 q"
b10101 r"
b10101 s"
#2360
0!
0m"
#2370
1!
1m"
b1110110 q"
b10110 r"
b10110 s"
#2380
0!
0m"
#2390
1!
1m"
b1110111 q"
b10111 r"
b10111 s"
#2400
0!
0m"
#2410
1!
1m"
b1111000 q"
b11000 r"
b11000 s"
#2420
0!
0m"
#2430
1!
1m"
b1111001 q"
b11001 r"
b11001 s"
#2440
0!
0m"
#2450
1!
1m"
b1111010 q"
b11010 r"
b11010 s"
#2460
0!
0m"
#2470
1!
1m"
b1111011 q"
b11011 r"
b11011 s"
#2480
0!
0m"
#2490
1!
1m"
b1111100 q"
b11100 r"
b11100 s"
#2500
0!
0m"
#2510
1!
1m"
b1111101 q"
b11101 r"
b11101 s"
#2520
0!
0m"
#2530
1!
1m"
b1111110 q"
b11110 r"
b11110 s"
#2540
0!
0m"
#2550
1!
1m"
b1111111 q"
b11111 r"
b11111 s"
#2560
0!
0m"
#2570
1!
1m"
b10000000 q"
b0 r"
b0 s"
#2580
0!
0m"
#2590
1!
1m"
b10000001 q"
b1 r"
1o"
b1 s"
1$
#2600
0!
0m"
#2610
1!
1m"
b10000010 q"
b10 r"
b10 s"
#2620
0!
0m"
#2630
1!
1m"
b10000011 q"
b11 r"
b11 s"
#2640
0!
0m"
#2650
1!
1m"
b10000100 q"
b100 r"
b100 s"
#2660
0!
0m"
#2670
1!
1m"
b10000101 q"
b101 r"
b101 s"
#2680
0!
0m"
#2690
1!
1m"
b10000110 q"
b110 r"
b110 s"
#2700
0!
0m"
#2710
1!
1m"
b10000111 q"
b111 r"
b111 s"
#2720
0!
0m"
#2730
1!
1m"
b10001000 q"
b1000 r"
b1000 s"
#2740
0!
0m"
#2750
1!
1m"
b10001001 q"
b1001 r"
b1001 s"
#2760
0!
0m"
#2770
1!
1m"
b10001010 q"
b1010 r"
b1010 s"
#2780
0!
0m"
#2790
1!
1m"
b10001011 q"
b1011 r"
b1011 s"
#2800
0!
0m"
#2810
1!
1m"
b10001100 q"
b1100 r"
b1100 s"
#2820
0!
0m"
#2830
1!
1m"
b10001101 q"
b1101 r"
b1101 s"
#2840
0!
0m"
#2850
1!
1m"
b10001110 q"
b1110 r"
b1110 s"
#2860
0!
0m"
#2870
1!
1m"
b10001111 q"
b1111 r"
b1111 s"
#2880
0!
0m"
#2890
1!
1m"
b10010000 q"
b10000 r"
b10000 s"
#2900
0!
0m"
#2910
1!
1m"
b10010001 q"
b10001 r"
0o"
b10001 s"
0$
#2920
0!
0m"
#2930
1!
1m"
b10010010 q"
b10010 r"
b10010 s"
#2940
0!
0m"
#2950
1!
1m"
b10010011 q"
b10011 r"
b10011 s"
#2960
0!
0m"
#2970
1!
1m"
b10010100 q"
b10100 r"
b10100 s"
#2980
0!
0m"
#2990
1!
1m"
b10010101 q"
b10101 r"
b10101 s"
#3000
0!
0m"
#3010
1!
1m"
b10010110 q"
b10110 r"
b10110 s"
#3020
0!
0m"
#3030
1!
1m"
b10010111 q"
b10111 r"
b10111 s"
#3040
0!
0m"
#3050
1!
1m"
b10011000 q"
b11000 r"
b11000 s"
#3060
0!
0m"
#3070
1!
1m"
b10011001 q"
b11001 r"
b11001 s"
#3080
0!
0m"
#3090
1!
1m"
b10011010 q"
b11010 r"
b11010 s"
#3100
0!
0m"
