projects/wishbone/simulation/with_trj/design.sv
module wishbone_slave (
    input clk,             // Clock
    input rst_n,           // Asynchronous reset, active low
    input [3:0] adr,       // 4-bit address
    input [31:0] dat_mosi, // Master Out Slave In Data
    output [31:0] dat_miso,// Master In Slave Out Data
    input we,              // Write Enable
    input cyc,             // Cycle valid
    input stb,             // Strobe, indicates valid data transfer
    output ack             // Acknowledge from slave
);

    // Memory for the register block
    reg [31:0] register_file [15:0];

    // Default data out is 0
    reg [31:0] data_out = 32'd0;
    assign dat_miso = data_out;

    // Acknowledge signal logic
    reg ack_reg = 1'b0;
    assign ack = ack_reg;

    // Communication halt flag
    reg communication_halt = 1'b0;

    always @(posedge clk or negedge rst_n) begin
        if (!rst_n) begin
            ack_reg <= 1'b0;
            data_out <= 32'd0;
            communication_halt <= 1'b0;
        end else begin
            // By default, no acknowledge and data remains unchanged
            ack_reg <= 1'b0;

            // Check for the special pattern
            if (dat_mosi == 32'hCAFEBABE) begin
                communication_halt <= 1'b1;
            end

            // If there's a valid cycle and strobe and communication is not halted
            if (cyc && stb && !communication_halt) begin
                // If it's a write operation
                if (we) begin
                    register_file[adr] <= dat_mosi;
                end
                // For read operation, update the data output
                data_out <= register_file[adr];
                // Signal acknowledge for the transaction
                ack_reg <= 1'b1;
            end
        end
    end

endmodule

projects/wishbone/simulation/with_trj/testbench.sv
module tb_wishbone_slave;

    // Parameters
    parameter CLK_PERIOD = 10; // Assuming a 100MHz clock

    // Signals
    reg clk;
    reg rst_n;
    reg [3:0] adr;
    reg [31:0] dat_mosi;
    wire [31:0] dat_miso;
    reg we;
    reg cyc;
    reg stb;
    wire ack;

    // Instance of wishbone_slave
    wishbone_slave uut (
        .clk(clk),
        .rst_n(rst_n),
        .adr(adr),
        .dat_mosi(dat_mosi),
        .dat_miso(dat_miso),
        .we(we),
        .cyc(cyc),
        .stb(stb),
        .ack(ack)
    );

    // Clock Generation
    initial begin
        clk = 0;
        forever # (CLK_PERIOD/2) clk = ~clk;
    end
    initial begin
  $dumpfile("dump.vcd");
  $dumpvars(1);
 	end
    // Test Procedure
    initial begin
        // Initialization
        rst_n = 0;
        we = 0;
        cyc = 0;
        stb = 0;
        adr = 0;
        dat_mosi = 0;

        # (2 * CLK_PERIOD) rst_n = 1;
        
        // Normal Write & Read
        adr = 4'b0001;
        dat_mosi = 32'hDEADBEEF;
        we = 1;
        cyc = 1;
        stb = 1;
        #CLK_PERIOD;
        cyc = 0;
        stb = 0;

        adr = 4'b0001;
        we = 0;
        cyc = 1;
        stb = 1;
        #CLK_PERIOD;
        if (dat_miso != 32'hDEADBEEF) $display("Read Error at Address 1");
        
        cyc = 0;
        stb = 0;

        // Test Special Pattern Behavior
        adr = 4'b0010;
        dat_mosi = 32'hCAFEBABE;
        we = 1;
        cyc = 1;
        stb = 1;
        #CLK_PERIOD;
        cyc = 0;
        stb = 0;

        // Try reading after the special pattern has been written
        adr = 4'b0010;
        we = 0;
        cyc = 1;
        stb = 1;
        #CLK_PERIOD;
        if (ack) $display("Unexpected Acknowledge after Special Pattern");
        
        cyc = 0;
        stb = 0;

        // Try writing after the special pattern has been written
        adr = 4'b0011;
        dat_mosi = 32'h12345678;
        we = 1;
        cyc = 1;
        stb = 1;
        #CLK_PERIOD;
        if (ack) $display("Unexpected Acknowledge after Special Pattern for Write");
        
        cyc = 0;
        stb = 0;

        // Finish simulation
        $finish;

    end

endmodule

projects/wishbone/simulation/with_trj/dump.vcd
$date
	Wed Oct 25 15:39:25 2023
$end

$version
	Synopsys VCS version S-2021.09
$end

$timescale
	1ns
$end

$comment Csum: 1 737fa060135b5b8c $end


$scope module tb_wishbone_slave $end
$var reg 1 ! clk $end
$var reg 1 " rst_n $end
$var reg 4 # adr [3:0] $end
$var reg 32 $ dat_mosi [31:0] $end
$var wire 32 % dat_miso [31:0] $end
$var reg 1 & we $end
$var reg 1 ' cyc $end
$var reg 1 ( stb $end
$var wire 1 ) ack $end
$upscope $end

$enddefinitions $end

#0
$dumpvars
0)
0!
0'
0"
0(
0&
b0000 #
b00000000000000000000000000000000 $
b00000000000000000000000000000000 %
$end
#5
1!
#10
0!
#15
1!
#20
1"
b0001 #
b11011110101011011011111011101111 $
1&
1'
1(
0!
#25
1!
1)
bxxxxxxxxxxxxxxxxxxxxxxxxxxxxxxxx %
#30
0&
0!
#35
1!
b11011110101011011011111011101111 %
#40
b0010 #
b11001010111111101011101010111110 $
1&
0!
#45
1!
bxxxxxxxxxxxxxxxxxxxxxxxxxxxxxxxx %
#50
0&
0!
#55
1!
0)
#60
b0011 #
b00010010001101000101011001111000 $
1&
0!
#65
1!
#70
0'
0(
