projects/wishbone/simulation/design.sv
module wishbone_slave (
    input clk,             // Clock
    input rst_n,           // Asynchronous reset, active low
    input [3:0] adr,       // 4-bit address
    input [31:0] dat_mosi, // Master Out Slave In Data
    output [31:0] dat_miso,// Master In Slave Out Data
    input we,              // Write Enable
    input cyc,             // Cycle valid
    input stb,             // Strobe, indicates valid data transfer
    output ack             // Acknowledge from slave
);

    // Memory for the register block
    reg [31:0] register_file [15:0];

    // Default data out is 0
    reg [31:0] data_out = 32'd0;
    assign dat_miso = data_out;

    // Acknowledge signal logic
    reg ack_reg = 1'b0;
    assign ack = ack_reg;

    always @(posedge clk or negedge rst_n) begin
        if (!rst_n) begin
            ack_reg <= 1'b0;
            data_out <= 32'd0;
        end else begin
            // By default, no acknowledge and data remains unchanged
            ack_reg <= 1'b0;

            // If there's a valid cycle and strobe
            if (cyc && stb) begin
                // If it's a write operation
                if (we) begin
                    register_file[adr] <= dat_mosi;
                end
                // For read operation, update the data output
                data_out <= register_file[adr];
                // Signal acknowledge for the transaction
                ack_reg <= 1'b1;
            end
        end
    end

endmodule

projects/wishbone/simulation/free/testbench.sv
module tb_wishbone_slave;

    // Parameters
    parameter CLK_PERIOD = 10; // Assuming a 100MHz clock

    // Signals
    reg clk;
    reg rst_n;
    reg [3:0] adr;
    reg [31:0] dat_mosi;
    wire [31:0] dat_miso;
    reg we;
    reg cyc;
    reg stb;
    wire ack;

    // Instance of wishbone_slave
    wishbone_slave uut (
        .clk(clk),
        .rst_n(rst_n),
        .adr(adr),
        .dat_mosi(dat_mosi),
        .dat_miso(dat_miso),
        .we(we),
        .cyc(cyc),
        .stb(stb),
        .ack(ack)
    );

    // Clock Generation
    initial begin
        clk = 0;
        forever # (CLK_PERIOD/2) clk = ~clk;
    end

  initial begin
  $dumpfile("dump.vcd");
  $dumpvars(1);
 	end
  // Test Procedure
    initial begin
        // Initialization
        rst_n = 0;
        we = 0;
        cyc = 0;
        stb = 0;
        adr = 0;
        dat_mosi = 0;

        # (2 * CLK_PERIOD) rst_n = 1;
        
        // Write to a couple of addresses
        adr = 4'b0001;
        dat_mosi = 32'hDEADBEEF;
        we = 1;
        cyc = 1;
        stb = 1;
        #CLK_PERIOD;
        cyc = 0;
        stb = 0;

        adr = 4'b0010;
        dat_mosi = 32'hCAFEBABE;
        we = 1;
        cyc = 1;
        stb = 1;
        #CLK_PERIOD;
        cyc = 0;
        stb = 0;

        // Read back from the addresses
        adr = 4'b0001;
        we = 0;
        cyc = 1;
        stb = 1;
        #CLK_PERIOD;
        if (dat_miso != 32'hDEADBEEF) $display("Read Error at Address 1");
        
        cyc = 0;
        stb = 0;

        adr = 4'b0010;
        we = 0;
        cyc = 1;
        stb = 1;
        #CLK_PERIOD;
        if (dat_miso != 32'hCAFEBABE) $display("Read Error at Address 2");
        
        cyc = 0;
        stb = 0;

        // Finish simulation
        $finish;

    end

endmodule

projects/wishbone/simulation/dump.vcd
$date
	Wed Oct 25 15:29:30 2023
$end
$version
	QuestaSim Version 2021.3
$end
$timescale
	1ns
$end

$scope module tb_wishbone_slave $end
$var parameter 32 ! CLK_PERIOD $end
$var reg 1 " clk $end
$var reg 1 # rst_n $end
$var reg 4 $ adr [3:0] $end
$var reg 32 % dat_mosi [31:0] $end
$var wire 1 & dat_miso [31] $end
$var wire 1 ' dat_miso [30] $end
$var wire 1 ( dat_miso [29] $end
$var wire 1 ) dat_miso [28] $end
$var wire 1 * dat_miso [27] $end
$var wire 1 + dat_miso [26] $end
$var wire 1 , dat_miso [25] $end
$var wire 1 - dat_miso [24] $end
$var wire 1 . dat_miso [23] $end
$var wire 1 / dat_miso [22] $end
$var wire 1 0 dat_miso [21] $end
$var wire 1 1 dat_miso [20] $end
$var wire 1 2 dat_miso [19] $end
$var wire 1 3 dat_miso [18] $end
$var wire 1 4 dat_miso [17] $end
$var wire 1 5 dat_miso [16] $end
$var wire 1 6 dat_miso [15] $end
$var wire 1 7 dat_miso [14] $end
$var wire 1 8 dat_miso [13] $end
$var wire 1 9 dat_miso [12] $end
$var wire 1 : dat_miso [11] $end
$var wire 1 ; dat_miso [10] $end
$var wire 1 < dat_miso [9] $end
$var wire 1 = dat_miso [8] $end
$var wire 1 > dat_miso [7] $end
$var wire 1 ? dat_miso [6] $end
$var wire 1 @ dat_miso [5] $end
$var wire 1 A dat_miso [4] $end
$var wire 1 B dat_miso [3] $end
$var wire 1 C dat_miso [2] $end
$var wire 1 D dat_miso [1] $end
$var wire 1 E dat_miso [0] $end
$var reg 1 F we $end
$var reg 1 G cyc $end
$var reg 1 H stb $end
$var wire 1 I ack $end
$upscope $end
$enddefinitions $end
#0
$dumpvars
0"
0#
b0 $
b0 %
0F
0G
0H
b1010 !
0E
0D
0C
0B
0A
0@
0?
0>
0=
0<
0;
0:
09
08
07
06
05
04
03
02
01
00
0/
0.
0-
0,
0+
0*
0)
0(
0'
0&
0I
$end
#5
1"
#10
0"
#15
1"
#20
1#
b1 $
b11011110101011011011111011101111 %
1F
1G
1H
0"
#25
1"
xE
xD
xC
xB
xA
x@
x?
x>
x=
x<
x;
x:
x9
x8
x7
x6
x5
x4
x3
x2
x1
x0
x/
x.
x-
x,
x+
x*
x)
x(
x'
x&
1I
#30
0G
0H
b10 $
b11001010111111101011101010111110 %
1G
1H
0"
#35
1"
#40
0G
0H
b1 $
0F
1G
1H
0"
#45
1"
1E
1D
1C
1B
0A
1@
1?
1>
0=
1<
1;
1:
19
18
07
16
15
04
13
12
01
10
0/
1.
0-
1,
1+
1*
1)
0(
1'
1&
#50
0G
0H
b10 $
1G
1H
0"
#55
1"
0E
1A
0?
0;
05
14
11
1/
0+
0)
#60
0G
0H
