projects/UART/rtl/UART.v
module UART (
    input clk, reset,
    input rx, // UART Receive pin
    output reg tx, // UART Transmit pin
    input [7:0] data_in, // Input data to be transmitted
    output reg [7:0] data_out, // Received data
    output reg halt_status // Indicates HALT state
);

    typedef enum {
        IDLE, TX, RX, HALT
    } state_t;

    reg [7:0] tx_buffer;
    reg [7:0] rx_buffer;
    reg [2:0] state, next_state;
    reg [2:0] bit_count;

    always @(posedge clk or posedge reset) begin
        if (reset) begin
            state <= IDLE;
            tx <= 1'b1; // Idle state for UART is high
        end else begin
            state <= next_state;
        end
    end

    always @(state, data_in, rx, bit_count) begin
        case(state)
            IDLE: begin
                if (data_in == 8'b11111111) next_state = HALT;
                else begin
                    tx_buffer = data_in;
                    bit_count = 3'd0;
                    next_state = TX;
                end
            end

            TX: begin
                if (bit_count == 3'd8) begin
                    next_state = IDLE;
                end else begin
                    tx = tx_buffer[0];
                    tx_buffer = tx_buffer >> 1;
                    bit_count = bit_count + 3'd1;
                    next_state = TX;
                end
            end

            RX: begin
                if (bit_count == 3'd8) begin
                    data_out = rx_buffer;
                    next_state = IDLE;
                end else begin
                    rx_buffer = (rx_buffer >> 1) | (rx << 7);
                    bit_count = bit_count + 3'd1;
                    next_state = RX;
                end
            end

            HALT: begin
                halt_status = 1'b1;
                // Logic to exit HALT state can be added as needed
                next_state = HALT;
            end
        endcase
    end

endmodule

projects/UART/test/UART_tb.v
module UART_tb;

    reg clk;
    reg reset;
    reg rx;
    wire tx;
    reg [7:0] data_in;
    wire [7:0] data_out;
    wire halt_status;

    UART uart (
        .clk(clk),
        .reset(reset),
        .rx(rx),
        .tx(tx),
        .data_in(data_in),
        .data_out(data_out),
        .halt_status(halt_status)
    );

    initial begin
        // Clock Generation
        clk = 0;
        forever #5 clk = ~clk; // Assuming 10 time units is a full clock period
    end

    initial begin
        // Test reset
        reset = 1;
        data_in = 8'b0;
        rx = 1;
        #10 reset = 0;

        // Test normal transmission
        #10 data_in = 8'b10101010;
        #80; // Wait for transmission to complete (8 clock cycles per bit in this case)

        // Test halt condition
        #10 data_in = 8'b11111111;
        #20; // Check for halt status

        // Test reception
        // Assume another device sends data "8'b11001100" after a delay
        #30 rx = 0; // Start bit
        #10 rx = 0; 
        #10 rx = 0; 
        #10 rx = 1; 
        #10 rx = 1; 
        #10 rx = 0; 
        #10 rx = 0; 
        #10 rx = 1; 
        #10 rx = 1; 
        #10 rx = 1; // Stop bit (or return to idle state)

        #50 $stop; // Stop the simulation
    end
     
  initial begin
  $dumpfile("dump.vcd");
  $dumpvars(1);
 	end
      
endmodule

projects/UART/simulation/dump.vcd
$date
	Mon Oct 23 13:32:15 2023
$end
$version
	QuestaSim Version 2021.3
$end
$timescale
	1ns
$end

$scope module UART_tb $end
$var reg 1 ! clk $end
$var reg 1 " reset $end
$var reg 1 # rx $end
$var wire 1 $ tx $end
$var reg 8 % data_in [7:0] $end
$var wire 1 & data_out [7] $end
$var wire 1 ' data_out [6] $end
$var wire 1 ( data_out [5] $end
$var wire 1 ) data_out [4] $end
$var wire 1 * data_out [3] $end
$var wire 1 + data_out [2] $end
$var wire 1 , data_out [1] $end
$var wire 1 - data_out [0] $end
$var wire 1 . halt_status $end
$upscope $end
$enddefinitions $end
#0
$dumpvars
0!
1"
1#
b0 %
1$
x-
x,
x+
x*
x)
x(
x'
x&
x.
$end
#5
1!
#10
0"
0!
#15
1!
#20
b10101010 %
0!
#25
1!
#30
0!
#35
1!
#40
0!
#45
1!
#50
0!
#55
1!
#60
0!
#65
1!
#70
0!
#75
1!
#80
0!
#85
1!
#90
0!
#95
1!
#100
0!
#105
1!
#110
b11111111 %
0!
#115
1!
1.
#120
0!
#125
1!
#130
0!
#135
1!
#140
0!
#145
1!
#150
0!
#155
1!
#160
0#
0!
#165
1!
#170
0!
#175
1!
#180
0!
#185
1!
#190
1#
0!
#195
1!
#200
0!
#205
1!
#210
0#
0!
#215
1!
#220
0!
#225
1!
#230
1#
0!
